duckdb_llm_udf/__init__.py
duckdb_llm_udf/llm_udf.py
duckdb_llm_udf-0.1.4.dist-info/licenses/LICENSE
duckdb_llm_udf-0.1.4.dist-info/METADATA
duckdb_llm_udf-0.1.4.dist-info/WHEEL
duckdb_llm_udf-0.1.4.dist-info/top_level.txt
duckdb_llm_udf-0.1.4.dist-info/RECORD
