Metadata-Version: 2.4
Name: duckdb-llm-udf
Version: 0.1.4
Summary: LLM UDF extension for DuckDB (Python interface)
Home-page: https://github.com/yourusername/duckdb_llm_udf
Author: Your Name
Author-email: Your Name <your@email.com>
License: MIT License
Requires-Python: >=3.9
License-File: LICENSE
Requires-Dist: duckdb>=0.8.0
Requires-Dist: python-dotenv>=0.19.0
Requires-Dist: numpy>=1.21.0
Provides-Extra: openai
Requires-Dist: openai>=1.0.0; extra == "openai"
Provides-Extra: anthropic
Requires-Dist: anthropic>=0.5.0; extra == "anthropic"
Provides-Extra: all
Requires-Dist: openai>=1.0.0; extra == "all"
Requires-Dist: anthropic>=0.5.0; extra == "all"
Dynamic: author
Dynamic: home-page
Dynamic: license-file
Dynamic: requires-python
